tyko/__init__.py
tyko/client.py
tyko/environment.py
tyko/types.py
tyko-0.1.11.dist-info/METADATA
tyko-0.1.11.dist-info/WHEEL
tyko-0.1.11.dist-info/RECORD
