Metadata-Version: 2.4
Name: tyko
Version: 0.1.11
Summary: Official Python SDK for Tyko Labs - Track experiments, manage models, and version datasets
Project-URL: Homepage, https://tyko-labs.com
Project-URL: Documentation, https://tyko-labs.com/docs
Author-email: Tyko Labs <contact@tyko-labs.com>
Keywords: experiment-tracking,machine-learning,mlops,model-management
Classifier: Development Status :: 3 - Alpha
Classifier: Intended Audience :: Developers
Classifier: Intended Audience :: Science/Research
Classifier: License :: OSI Approved :: MIT License
Classifier: Programming Language :: Python :: 3
Classifier: Programming Language :: Python :: 3.11
Classifier: Programming Language :: Python :: 3.12
Classifier: Programming Language :: Python :: 3.13
Classifier: Topic :: Scientific/Engineering :: Artificial Intelligence
Requires-Python: >=3.11
Requires-Dist: httpx~=0.24
Requires-Dist: typing-extensions~=4.15
Provides-Extra: dev
Requires-Dist: black~=25.12; extra == 'dev'
Requires-Dist: mkdocs>=1.5.0; extra == 'dev'
Requires-Dist: mkdocstrings[python]~=1.0; extra == 'dev'
Requires-Dist: mypy~=1.19; extra == 'dev'
Requires-Dist: pytest-cov~=7.0; extra == 'dev'
Requires-Dist: pytest-httpx~=0.22; extra == 'dev'
Requires-Dist: pytest~=9.0; extra == 'dev'
Requires-Dist: ruff~=0.14; extra == 'dev'
Requires-Dist: types-requests~=2.32.4; extra == 'dev'
